{
	"configurations" : 
	[
		{
			"directories" : 
			[
				{
					"build" : ".",
					"jsonFile" : "directory-.-debug-f5ebdc15457944623624.json",
					"minimumCMakeVersion" : 
					{
						"string" : "3.10.0"
					},
					"projectIndex" : 0,
					"source" : ".",
					"targetIndexes" : 
					[
						0
					]
				}
			],
			"name" : "debug",
			"projects" : 
			[
				{
					"directoryIndexes" : 
					[
						0
					],
					"name" : "freertos_hello_cm7",
					"targetIndexes" : 
					[
						0
					]
				}
			],
			"targets" : 
			[
				{
					"directoryIndex" : 0,
					"id" : "freertos_hello_cm7.elf::@6890427a1f51a3e7e1df",
					"jsonFile" : "target-freertos_hello_cm7.elf-debug-868eab3c798c26de2ab5.json",
					"name" : "freertos_hello_cm7.elf",
					"projectIndex" : 0
				}
			]
		}
	],
	"kind" : "codemodel",
	"paths" : 
	{
		"build" : "/home/stvsl/Documents/DOTRUST/PortingTest/imxrt1170_freertos_qt/armgcc/debug",
		"source" : "/home/stvsl/Documents/DOTRUST/PortingTest/imxrt1170_freertos_qt/armgcc"
	},
	"version" : 
	{
		"major" : 2,
		"minor" : 7
	}
}
